standup_roulette/__init__.py
standup_roulette/standup_roulette.py
standup_roulette-0.2.dist-info/METADATA
standup_roulette-0.2.dist-info/WHEEL
standup_roulette-0.2.dist-info/entry_points.txt
standup_roulette-0.2.dist-info/top_level.txt
standup_roulette-0.2.dist-info/RECORD
