Metadata-Version: 2.1
Name: standup-roulette
Version: 0.2
Summary: Standup helper: Finds the person who starts and the direction (also for online meetings).
Home-page: UNKNOWN
Author: Timo
Author-email: UNKNOWN
License: UNKNOWN
Platform: UNKNOWN
